{
  "run_id": "verify_proof_stage2_solver0_20260531_015132",
  "started": "2026-05-31T01:51:32.618294",
  "stages": {
    "annotate": {
      "steps_parsed": 5,
      "by_confidence": {
        "CONFIDENT": 4,
        "APPROX": 0,
        "UNABLE TO LOCATE": 1
      }
    },
    "identity_check": {
      "burago__geometric_inequalities": {
        "verdict": false,
        "reason": "VERDICT: NO\nReason: The candidate PDF is a 2022 paper by Ramon van Handel that references the expected book, not the 1988 book by Burago and Zalgaller itself."
      },
      "federer__geometric_measure_theory": {
        "verdict": true,
        "reason": "VERDICT: YES\nReason: The author, title, and year (\"1969 Edition\") exactly match the expected citation."
      },
      "fonseca__degree_theory_in_analysis_and_applications": {
        "verdict": false,
        "reason": "VERDICT: NO\nReason: The candidate PDF is a completely different paper titled \"On the total variation of the Jacobian\" by Fonseca, Fusco, and Marcellini (2003), not \"Degree Theory in Analysis and Appli"
      },
      "gromov__metric_structures_for_riemannian_and_non_riemannia": {
        "verdict": false,
        "reason": "VERDICT: NO\nReason: The page only shows a generic publisher's blurb for \"Modern Birkhauser Classics\" and lacks the author and title."
      },
      "guth__volumes_of_balls_in_large_riemannian_manifolds": {
        "verdict": true,
        "reason": "VERDICT: YES\nReason: The title, author (Larry Guth), and year (2011) all perfectly match the expected citation."
      },
      "morgan__geometric_measure_theory_a_beginner_s_guide": {
        "verdict": true,
        "reason": "VERDICT: YES\nReason: The title matches exactly, confirming it is the requested work despite being a later edition."
      }
    },
    "verify": {
      "n": 2,
      "verdicts": {
        "SUPPORTS": 0,
        "DOES NOT APPLY": 0,
        "CONTRADICTS": 0,
        "NOT FOUND": 2,
        "UNKNOWN": 0
      }
    },
    "unmatched": [
      2,
      4,
      5
    ]
  },
  "finished": "2026-05-31T02:02:03.658447"
}